sam2lca/__init__.py
sam2lca/acc2tax.py
sam2lca/check_conserved_regions.py
sam2lca/cli.py
sam2lca/lca.py
sam2lca/main.py
sam2lca/parse_alignment.py
sam2lca/rocksdb.py
sam2lca/taxonomy.py
sam2lca/utils.py
sam2lca/write_alignment.py
sam2lca-1.1.4.dist-info/LICENSE
sam2lca-1.1.4.dist-info/METADATA
sam2lca-1.1.4.dist-info/WHEEL
sam2lca-1.1.4.dist-info/entry_points.txt
sam2lca-1.1.4.dist-info/top_level.txt
sam2lca-1.1.4.dist-info/RECORD
