Metadata-Version: 2.1
Name: sam2lca
Version: 1.1.4
Summary: Lowest Common Ancestor on SAM/BAM/CRAM alignment files
Home-page: https://github.com/maxibor/sam2lca
License: GNU-GPLv3
Platform: UNKNOWN
Requires-Python: >=3.6
License-File: LICENSE
Requires-Dist: click
Requires-Dist: pysam
Requires-Dist: tqdm
Requires-Dist: xopen
Requires-Dist: python-rocksdb
Requires-Dist: taxopy
Requires-Dist: pandas
Requires-Dist: scipy
Requires-Dist: numpy
